flake8_no_pytest_mark_only/__init__.py
flake8_no_pytest_mark_only/plugin.py
flake8_no_pytest_mark_only/py.typed
flake8_no_pytest_mark_only-1.0.0.dist-info/LICENSE
flake8_no_pytest_mark_only-1.0.0.dist-info/METADATA
flake8_no_pytest_mark_only-1.0.0.dist-info/WHEEL
flake8_no_pytest_mark_only-1.0.0.dist-info/entry_points.txt
flake8_no_pytest_mark_only-1.0.0.dist-info/top_level.txt
flake8_no_pytest_mark_only-1.0.0.dist-info/RECORD
