Metadata-Version: 2.1
Name: flake8-no-pytest-mark-only
Version: 1.0.0
Summary: Flake8 plugin to disallow the use of the pytest.mark.only decorator.
Author-email: František Nesveda <frantisek.nesveda@gmail.com>
License: Apache Software License
Project-URL: Homepage, https://www.nesveda/com/projects/flake8-no-pytest-mark-only
Project-URL: Documentation, https://github.com/fnesveda/flake8-no-pytest-mark-only
Project-URL: Source, https://github.com/fnesveda/flake8-no-pytest-mark-only
Project-URL: Issue tracker, https://github.com/fnesveda/flake8-no-pytest-mark-only/issues
Project-URL: Changelog, https://github.com/fnesveda/flake8-no-pytest-mark-only/blob/master/CHANGELOG.md
Keywords: flake8,pytest,mark,only
Classifier: Development Status :: 5 - Production/Stable
Classifier: Intended Audience :: Developers
Classifier: License :: OSI Approved :: Apache Software License
Classifier: Operating System :: OS Independent
Classifier: Programming Language :: Python :: 3.8
Classifier: Programming Language :: Python :: 3.9
Classifier: Programming Language :: Python :: 3.10
Classifier: Programming Language :: Python :: 3.11
Classifier: Topic :: Software Development :: Libraries
Requires-Python: >=3.8
License-File: LICENSE
Provides-Extra: dev
Requires-Dist: autopep8 ~=2.0.4 ; extra == 'dev'
Requires-Dist: build ~=1.0.0 ; extra == 'dev'
Requires-Dist: flake8 ~=6.1.0 ; extra == 'dev'
Requires-Dist: flake8-bugbear ~=23.7.10 ; extra == 'dev'
Requires-Dist: flake8-commas ~=2.1.0 ; extra == 'dev'
Requires-Dist: flake8-comprehensions ~=3.14.0 ; extra == 'dev'
Requires-Dist: flake8-docstrings ~=1.7.0 ; extra == 'dev'
Requires-Dist: flake8-isort ~=6.0.0 ; extra == 'dev'
Requires-Dist: flake8-noqa ~=1.3.2 ; extra == 'dev'
Requires-Dist: flake8-pytest-style ~=1.7.2 ; extra == 'dev'
Requires-Dist: flake8-quotes ~=3.3.2 ; extra == 'dev'
Requires-Dist: flake8-simplify ~=0.20.0 ; extra == 'dev'
Requires-Dist: flake8-unused-arguments ~=0.0.13 ; extra == 'dev'
Requires-Dist: isort ~=5.12.0 ; extra == 'dev'
Requires-Dist: mypy ~=1.5.1 ; extra == 'dev'
Requires-Dist: pep8-naming ~=0.13.3 ; extra == 'dev'
Requires-Dist: pre-commit ~=3.4.0 ; extra == 'dev'
Requires-Dist: pytest ~=7.4.1 ; extra == 'dev'
Requires-Dist: pytest-only ~=2.0.0 ; extra == 'dev'
Requires-Dist: twine ~=4.0.2 ; extra == 'dev'
